acoustic_analyser/__init__.py
acoustic_analyser/generate_equation_file.py
acoustic_analyser/main.py
acoustic_analyser/equations/fixed_end.pkl
acoustic_analyser/equations/free_end.pkl
acoustic_analyser/equations/two_member.pkl
acoustic_analyser/modules/bc.py
acoustic_analyser/modules/joint.py
acoustic_analyser/modules/member.py
acoustic_analyser/modules/rt_bc.py
acoustic_analyser/modules/rt_joint.py
acoustic_analyser-0.0.9.dist-info/METADATA
acoustic_analyser-0.0.9.dist-info/WHEEL
acoustic_analyser-0.0.9.dist-info/top_level.txt
acoustic_analyser-0.0.9.dist-info/RECORD
