Metadata-Version: 2.1
Name: acoustic-analyser
Version: 0.0.9
Summary: An Open Source package to perform nodal analysis on simple 2D structures using wave based approach
Home-page: https://github.com/Manofmomo/AcousticAnalyser
Author: Dhruv Bhatia, Dr. Abhijit Sarkar
Requires-Dist: sympy
Requires-Dist: numpy
Requires-Dist: scipy
Requires-Dist: matplotlib
